oc_dms_mirror/__init__.py
oc_dms_mirror/__main__.py
oc_dms_mirror/dms_mirror.py
oc_dms_mirror/rest_api/__init__.py
oc_dms_mirror/rest_api/__main__.py
oc_dms_mirror/rest_api/application.py
oc_dms_mirror/rest_api/config.py
oc_dms_mirror/rest_api/app/__init__.py
oc_dms_mirror/rest_api/app/routes.py
oc_dms_mirror-3.2.0.dist-info/licenses/LICENSE
oc_dms_mirror-3.2.0.dist-info/METADATA
oc_dms_mirror-3.2.0.dist-info/WHEEL
oc_dms_mirror-3.2.0.dist-info/top_level.txt
oc_dms_mirror-3.2.0.dist-info/RECORD
