Metadata-Version: 2.4
Name: oc-dms-mirror
Version: 3.2.0
Summary: Tool for mirroring DMS artifacts
License-File: LICENSE
Requires-Dist: oc-cdtapi>=3.29.1
Requires-Dist: oc-checksumsq>=10.0.3
Requires-Dist: flask
Requires-Dist: gunicorn==23.0.0
Requires-Dist: oc_logging==1.1.7
Dynamic: description
Dynamic: description-content-type
Dynamic: license-file
Dynamic: requires-dist
Dynamic: summary
